pipplusplus/__init__.py
pipplusplus/run.py
pipplusplus/setup.py
pipplusplus/pipper/__init__.py
pipplusplus/pipper/pipper_gen.py
pipplusplus/pipper/pipper_main.py
pipplusplus/utests/__init__.py
pipplusplus/utests/pipper/__init__.py
pipplusplus/utests/pipper/test_pipper.py
pipplusplus/utests/utils/__init__.py
pipplusplus/utests/utils/proxy/__init__.py
pipplusplus/utests/utils/proxy/test_proxy_setters.py
pipplusplus/utils/Validator.py
pipplusplus/utils/__init__.py
pipplusplus/utils/exceptions.py
pipplusplus/utils/file_searcher.py
pipplusplus/utils/url_msg_parser.py
pipplusplus/utils/proxy/__init__.py
pipplusplus/utils/proxy/proxy_setters.py
pipplusplus/view/__init__.py
pipplusplus/view/application/__init__.py
pipplusplus/view/application/flask_piper.py
pipplusplus/view/application/web_pipper_factory.py
pip_plus_plus-0.0.12.dist-info/METADATA
pip_plus_plus-0.0.12.dist-info/WHEEL
pip_plus_plus-0.0.12.dist-info/top_level.txt
pip_plus_plus-0.0.12.dist-info/RECORD
