Metadata-Version: 2.1
Name: pip-plus-plus
Version: 0.0.12
Summary: Pip++
Home-page: https://github.com/idan57/pip-plus-plus
Author: Idan Cohen
Author-email: idan57@gmail.com
License: UNKNOWN
Platform: UNKNOWN
Classifier: Programming Language :: Python :: 3
Classifier: Operating System :: OS Independent
Requires-Python: >=3.6
Requires-Dist: flask
